CHANGES
INSTALL
LICENSE
MANIFEST.in
setup.py
jinjasql/__init__.py
jinjasql/core.py
jinjasql.egg-info/PKG-INFO
jinjasql.egg-info/SOURCES.txt
jinjasql.egg-info/dependency_links.txt
jinjasql.egg-info/requires.txt
jinjasql.egg-info/top_level.txt