Metadata-Version: 1.1
Name: jinjasql
Version: 0.1.7
Summary: Generate SQL Queries and Corresponding Bind Parameters using a Jinja2 Template
Home-page: https://github.com/hashedin/jinjasql
Author: Sripathi Krishnan
Author-email: Sripathi@hashedin.com
License: MIT
Download-URL: http://cloud.github.com/downloads/hashedin/jinjasql/jinjasql-0.1.7.tar.gz
Keywords: Jinja2,SQL,Python,Template
Platform: UNKNOWN
Classifier: Development Status :: 4 - Beta
Classifier: Environment :: Console
Classifier: Intended Audience :: Developers
Classifier: License :: OSI Approved :: MIT License
Classifier: Operating System :: OS Independent
Classifier: Programming Language :: Python
Classifier: Programming Language :: Python :: 2.7
Classifier: Programming Language :: Python :: 3
Classifier: Programming Language :: Python :: 3.3
Classifier: Programming Language :: Python :: 3.4
Classifier: Programming Language :: Python :: 3.5
